pitop/processing/__init__.py
pitop/processing/algorithms/__init__.py
pitop/processing/algorithms/ball_detect.py
pitop/processing/algorithms/hsv_color_ranges.py
pitop/processing/algorithms/line_detect.py
pitop/processing/algorithms/faces/__init__.py
pitop/processing/algorithms/faces/emotion_classifier.py
pitop/processing/algorithms/faces/face_detector.py
pitop/processing/algorithms/faces/core/__init__.py
pitop/processing/algorithms/faces/core/emotion.py
pitop/processing/algorithms/faces/core/face.py
pitop/processing/algorithms/faces/core/face_utils.py
pitop/processing/core/__init__.py
pitop/processing/core/load_models.py
pitop/processing/core/math_functions.py
pitop/processing/core/vision_functions.py
pitop.processing-0.34.3.post1.dist-info/METADATA
pitop.processing-0.34.3.post1.dist-info/WHEEL
pitop.processing-0.34.3.post1.dist-info/top_level.txt
pitop.processing-0.34.3.post1.dist-info/RECORD
